tldream/__init__.py
tldream/_version.py
tldream/cldm_v15.yaml
tldream/const.py
tldream/language.py
tldream/server.py
tldream/shared.py
tldream/socket_manager.py
tldream/util.py
tldream/web_config.py
tldream/assets/.DS_Store
tldream/assets/16bitscene.png
tldream/assets/Complex-Lineart.png
tldream/assets/Van-Gogh.jpeg
tldream/assets/anything-v3.0.png
tldream/assets/artstation.jpg
tldream/assets/dreamlike.jpg
tldream/assets/dreamshaper.jpg
tldream/assets/epic.png
tldream/assets/ghibli-diffusion-samples-02s.jpg
tldream/assets/guofeng.jpg
tldream/assets/inkpunk.jpg
tldream/assets/knollingcase.jpg
tldream/assets/modi-samples-02s.jpg
tldream/assets/pokemon.png
tldream/assets/redshift1.jpeg
tldream/assets/redshift2.jpeg
tldream/assets/robo.png
tldream/assets/snthwve.jpg
tldream/assets/stable_diffusion_12_1.png
tldream/assets/vectorartz.png
tldream/assets/waifu.png
tldream/cldm/__init__.py
tldream/cldm/cldm.py
tldream/cldm/hack.py
tldream/cldm/model.py
tldream/ldm/__init__.py
tldream/ldm/util.py
tldream/ldm/models/__init__.py
tldream/ldm/models/autoencoder.py
tldream/ldm/models/diffusion/__init__.py
tldream/ldm/models/diffusion/ddim.py
tldream/ldm/models/diffusion/ddpm.py
tldream/ldm/models/diffusion/plms.py
tldream/ldm/models/diffusion/sampling_util.py
tldream/ldm/models/diffusion/dpm_solver/__init__.py
tldream/ldm/models/diffusion/dpm_solver/dpm_solver.py
tldream/ldm/models/diffusion/dpm_solver/sampler.py
tldream/ldm/models/diffusion/uni_pc/__init__.py
tldream/ldm/models/diffusion/uni_pc/sampler.py
tldream/ldm/models/diffusion/uni_pc/uni_pc.py
tldream/ldm/modules/__init__.py
tldream/ldm/modules/attention.py
tldream/ldm/modules/ema.py
tldream/ldm/modules/diffusionmodules/__init__.py
tldream/ldm/modules/diffusionmodules/model.py
tldream/ldm/modules/diffusionmodules/openaimodel.py
tldream/ldm/modules/diffusionmodules/upscaling.py
tldream/ldm/modules/diffusionmodules/util.py
tldream/ldm/modules/distributions/__init__.py
tldream/ldm/modules/distributions/distributions.py
tldream-0.6.1.dist-info/LICENSE
tldream-0.6.1.dist-info/METADATA
tldream-0.6.1.dist-info/WHEEL
tldream-0.6.1.dist-info/entry_points.txt
tldream-0.6.1.dist-info/top_level.txt
tldream-0.6.1.dist-info/RECORD
