Metadata-Version: 2.1
Name: tldream
Version: 0.6.1
Summary: A tiny little diffusion drawing app
Home-page: https://github.com/Sanster/tldream
Author: PanicByte
Author-email: cwq1913@gmail.com
License: UNKNOWN
Platform: UNKNOWN
Classifier: License :: OSI Approved :: Apache Software License
Classifier: Operating System :: OS Independent
Classifier: Programming Language :: Python :: 3
Classifier: Programming Language :: Python :: 3.7
Classifier: Programming Language :: Python :: 3.8
Classifier: Programming Language :: Python :: 3.9
Classifier: Programming Language :: Python :: 3.10
Classifier: Topic :: Scientific/Engineering :: Artificial Intelligence
Requires-Python: >=3.7
Requires-Dist: torch (>=1.13.1)
Requires-Dist: opencv-contrib-python
Requires-Dist: transformers (>=4.26.1)
Requires-Dist: diffusers (>=0.14.0)
Requires-Dist: accelerate (>=0.16.0)
Requires-Dist: omegaconf (==2.1.1)
Requires-Dist: einops (==0.3.0)
Requires-Dist: addict (==2.4.0)
Requires-Dist: yapf (==0.32.0)
Requires-Dist: fastapi[all]
Requires-Dist: python-multipart
Requires-Dist: typer
Requires-Dist: rich
Requires-Dist: loguru
Requires-Dist: python-socketio
Requires-Dist: safetensors
Requires-Dist: xformers
Requires-Dist: gradio
Requires-Dist: httpx[socks]
